LICENSE
MANIFEST.in
readme.rst
setup.cfg
setup.py
accessible_output3/__init__.py
accessible_output3.egg-info/PKG-INFO
accessible_output3.egg-info/SOURCES.txt
accessible_output3.egg-info/dependency_links.txt
accessible_output3.egg-info/not-zip-safe
accessible_output3.egg-info/requires.txt
accessible_output3.egg-info/top_level.txt
accessible_output3/lib/PCTKUSR.dll
accessible_output3/lib/PCTKUSR64.dll
accessible_output3/lib/SAAPI32.dll
accessible_output3/lib/ZDSRAPI.dll
accessible_output3/lib/ZDSRAPI_x64.dll
accessible_output3/lib/dolapi.dll
accessible_output3/lib/nvdaControllerClient32.dll
accessible_output3/lib/nvdaControllerClient64.dll
accessible_output3/outputs/__init__.py
accessible_output3/outputs/auto.py
accessible_output3/outputs/base.py
accessible_output3/outputs/dolphin.py
accessible_output3/outputs/e_speak.py
accessible_output3/outputs/jaws.py
accessible_output3/outputs/nsspeechsynthesizer.py
accessible_output3/outputs/nvda.py
accessible_output3/outputs/pc_talker.py
accessible_output3/outputs/sapi4.py
accessible_output3/outputs/sapi5.py
accessible_output3/outputs/speech_dispatcher.py
accessible_output3/outputs/system_access.py
accessible_output3/outputs/voiceover.py
accessible_output3/outputs/window_eyes.py
accessible_output3/outputs/zdsr.py